.drone.yml
.gitignore
README.rst
setup.cfg
setup.py
examples/conftest.py
examples/functions/__init__.py
examples/functions/test_concurrent.py
examples/functions/test_regular.py
examples/methods/__init__.py
examples/methods/test_concurrent.py
examples/methods/test_regular.py
pytest_yield/__init__.py
pytest_yield/fixtures.py
pytest_yield/mark.py
pytest_yield/newhooks.py
pytest_yield/plugin.py
pytest_yield/runner.py
pytest_yield.egg-info/PKG-INFO
pytest_yield.egg-info/SOURCES.txt
pytest_yield.egg-info/dependency_links.txt
pytest_yield.egg-info/entry_points.txt
pytest_yield.egg-info/requires.txt
pytest_yield.egg-info/top_level.txt