Metadata-Version: 1.1
Name: pytest-yield
Version: 0.2.9
Summary: PyTest plugin to run tests concurrently, each `yield` switch context to other one
Home-page: https://github.com/devova/pytest-yield
Author: Volodymyr Trotsyshyn
Author-email: devova@gmail.com
License: UNKNOWN
Keywords: testing,pytest
Platform: UNKNOWN
Classifier: Programming Language :: Python :: 2.7
Classifier: Programming Language :: Python :: 3.7
